openstaad/__init__.py
openstaad/command.py
openstaad/design.py
openstaad/geometry.py
openstaad/load.py
openstaad/output.py
openstaad/properties.py
openstaad/root.py
openstaad/support.py
openstaad/tools.py
openstaad/view.py
openstaad-0.0.13.dist-info/METADATA
openstaad-0.0.13.dist-info/WHEEL
openstaad-0.0.13.dist-info/licenses/LICENSE
openstaad-0.0.13.dist-info/RECORD
