Metadata-Version: 2.4
Name: openstaad
Version: 0.0.13
Summary: A small example package for openstaad python package
Project-URL: Homepage, https://github.com/OpenStaad/OpenStaadPython
Project-URL: Issues, https://github.com/OpenStaad/OpenStaadPython/issues
Author-email: konrad <opensteel611@example.com>
License: MIT License
License-File: LICENSE
Classifier: License :: OSI Approved :: MIT License
Classifier: Operating System :: OS Independent
Classifier: Programming Language :: Python :: 3
Classifier: Programming Language :: Python :: 3.10
Classifier: Programming Language :: Python :: 3.11
Classifier: Programming Language :: Python :: 3.12
Classifier: Programming Language :: Python :: 3.13
Classifier: Programming Language :: Python :: 3.14
Requires-Python: <3.15,>=3.10
Requires-Dist: comtypes==1.4.15
